{
  "firstLayout": "",
  "gdVersion": {
    "build": 99,
    "major": 4,
    "minor": 0,
    "revision": 0
  },
  "properties": {
    "adaptGameResolutionAtRuntime": false,
    "folderProject": true,
    "orientation": "default",
    "packageName": "com.gens",
    "pixelsRounding": true,
    "projectUuid": "3f13803d-cd22-4ac7-a71e-1ef16c34ff81",
    "scaleMode": "linear",
    "sizeOnStartupMode": "adaptWidth",
    "useExternalSourceFiles": false,
    "version": "1.0.0",
    "name": "GENS             ",
    "author": "",
    "windowWidth": 800,
    "windowHeight": 600,
    "latestCompilationDirectory": "",
    "maxFPS": 60,
    "minFPS": 60,
    "verticalSync": false,
    "platformSpecificAssets": {},
    "loadingScreen": {
      "backgroundColor": 0,
      "backgroundFadeInDuration": 0.2,
      "backgroundImageResourceName": "",
      "gdevelopLogoStyle": "light",
      "logoAndProgressFadeInDuration": 0.2,
      "logoAndProgressLogoFadeInDelay": 0.2,
      "minDuration": 1.5,
      "progressBarColor": 16777215,
      "progressBarHeight": 20,
      "progressBarMaxWidth": 200,
      "progressBarMinWidth": 40,
      "progressBarWidthPercent": 30,
      "showGDevelopSplash": true,
      "showProgressBar": true
    },
    "authorIds": [
      "SRpUmxpSPKQfTXDcpwsWojBfLUy1"
    ],
    "extensionProperties": [],
    "platforms": [
      {
        "name": "GDevelop JS platform"
      }
    ],
    "currentPlatform": "GDevelop JS platform"
  },
  "resources": {
    "resources": [
      {
        "alwaysLoaded": false,
        "file": "NewObject-1.png",
        "kind": "image",
        "metadata": "",
        "name": "NewObject-1.png",
        "smoothed": true,
        "userAdded": false
      },
      {
        "alwaysLoaded": false,
        "file": "a1-1.png",
        "kind": "image",
        "metadata": "",
        "name": "a1-1.png",
        "smoothed": true,
        "userAdded": false
      },
      {
        "file": "DTM-Mono.otf",
        "kind": "font",
        "metadata": "",
        "name": "DTM-Mono.otf",
        "userAdded": true
      },
      {
        "file": "retro.otf",
        "kind": "font",
        "metadata": "",
        "name": "retro.otf",
        "userAdded": false
      },
      {
        "alwaysLoaded": false,
        "file": "NewObject-1-0.png",
        "kind": "image",
        "metadata": "",
        "name": "NewObject-1-0.png",
        "smoothed": true,
        "userAdded": true
      },
      {
        "file": "12.mp3",
        "kind": "audio",
        "metadata": "",
        "name": "12.mp3",
        "preloadAsMusic": false,
        "preloadAsSound": false,
        "userAdded": true
      },
      {
        "file": "13.mp3",
        "kind": "audio",
        "metadata": "",
        "name": "13.mp3",
        "preloadAsMusic": false,
        "preloadAsSound": false,
        "userAdded": true
      },
      {
        "alwaysLoaded": false,
        "file": "g1-default-000.png",
        "kind": "image",
        "metadata": "",
        "name": "g1-default-000.png",
        "smoothed": true,
        "userAdded": false
      },
      {
        "alwaysLoaded": false,
        "file": "g1-default-0002.png",
        "kind": "image",
        "metadata": "",
        "name": "g1-default-0002.png",
        "smoothed": true,
        "userAdded": true
      },
      {
        "file": "6610.mp3",
        "kind": "audio",
        "metadata": "",
        "name": "6610.mp3",
        "preloadAsMusic": false,
        "preloadAsSound": false,
        "userAdded": true
      },
      {
        "disablePreload": false,
        "file": "a1.json",
        "kind": "json",
        "metadata": "",
        "name": "a1.json",
        "userAdded": true
      },
      {
        "file": "mus_cymbal.ogg",
        "kind": "audio",
        "metadata": "",
        "name": "mus_cymbal.ogg",
        "preloadAsMusic": false,
        "preloadAsSound": false,
        "userAdded": true
      },
      {
        "file": "003.wav",
        "kind": "audio",
        "metadata": "",
        "name": "003.wav",
        "preloadAsMusic": false,
        "preloadAsSound": false,
        "userAdded": false
      }
    ],
    "resourceFolders": []
  },
  "objects": [],
  "objectsGroups": [],
  "variables": [
    {
      "name": "speed",
      "type": "string",
      "value": "0.5"
    },
    {
      "name": "sp",
      "type": "string",
      "value": "1"
    }
  ],
  "layouts": [
    {
      "__REFERENCE_TO_SPLIT_OBJECT": true,
      "referenceTo": "/layouts/start2"
    },
    {
      "__REFERENCE_TO_SPLIT_OBJECT": true,
      "referenceTo": "/layouts/start4"
    },
    {
      "__REFERENCE_TO_SPLIT_OBJECT": true,
      "referenceTo": "/layouts/start3"
    },
    {
      "__REFERENCE_TO_SPLIT_OBJECT": true,
      "referenceTo": "/layouts/start"
    }
  ],
  "externalEvents": [
    {
      "__REFERENCE_TO_SPLIT_OBJECT": true,
      "referenceTo": "/externalEvents/newexternalevents"
    }
  ],
  "eventsFunctionsExtensions": [
    {
      "__REFERENCE_TO_SPLIT_OBJECT": true,
      "referenceTo": "/eventsFunctionsExtensions/linearmovement"
    }
  ],
  "externalLayouts": [],
  "externalSourceFiles": []
}